[
  {
    "id": 1,
    "question": "Koja je uloga aplikativnog sloja?",
    "answers": [
      "uspostavljanje komunikacije izmeðu krajnjih ureðaja",
      "prenos podataka izmeðu krajnjih čvorova mreže",
      "razmena poruka izmeðu mrežnih procesa",
      "razmena poruka izmeðu klijenata i servera"
    ],
    "correctAnswer": "razmena poruka izmeðu mrežnih procesa"
  },
  {
    "id": 2,
    "question": "U HTTP zahtevima imamo sledeće tipove komandi:",
    "answers": [
      "POST, GET, HEAD, PUT, DELETE",
      "LIST, RETR, STOR, QUIT",
      "GET, POST, MAIL FROM, RCPT TO",
      "HELO, MAIL FROM, RCPT TO, DATA, QUIT"
    ],
    "correctAnswer": "POST, GET, HEAD, PUT, DELETE"
  },
  {
    "id": 3,
    "question": "HTTP protokol čuva stanje na serveru kod sledećeg načina rada:",
    "answers": [
      "Kod oba metoda rada",
      "Postojana konekcija",
      "Nepostojana konekcija",
      "Ni kod jednog"
    ],
    "correctAnswer": "Ni kod jednog"
  },
  {
    "id": 4,
    "question": "Koliko različitih soketa može da postoji na jednom računaru?",
    "answers": [
      "1",
      "2^16",
      "2^32",
      "2^48"
    ],
    "correctAnswer": "2^16"
  },
  {
    "id": 5,
    "question": "Slanje HTTP upita bez očekivanja odgovora naziva se:",
    "answers": [
      "GET",
      "POST",
      "HTTP pipelining",
      "Nepostojana konekcija"
    ],
    "correctAnswer": "HTTP pipelining"
  },
  {
    "id": 6,
    "question": "U statusnom redu (reply header) imamo sledeće kodove:",
    "answers": [
      "200, 301, 400, 404, 505",
      "404 500 505",
      "200, 301, 404",
      "100, 200, 300, 400, 500"
    ],
    "correctAnswer": "200, 301, 400, 404, 505"
  },
  {
    "id": 7,
    "question": "SMTP je protokol za:",
    "answers": [
      "slanje e-mail poruka",
      "preuzimanje e-mail poruka",
      "slanje i preuzimanje e-mail poruka",
      "prenos datoteka"
    ],
    "correctAnswer": "slanje e-mail poruka"
  },
  {
    "id": 8,
    "question": "Kod e-mail komunikacije, kada Alice šalje Bobu email, koja komunikacija je push a koja pull?",
    "answers": [
      "Alice-Server push, Server-Bob pull",
      "Alice-Server pull, Server-Bob push",
      "Obe push",
      "Obe pull"
    ],
    "correctAnswer": "Alice-Server push, Server-Bob pull"
  },
  {
    "id": 9,
    "question": "Da li SMTP koristi postojanu vezu?",
    "answers": [
      "da",
      "ne",
      "zavisi od implementacije",
      "samo za velike poruke"
    ],
    "correctAnswer": "da"
  },
  {
    "id": 10,
    "question": "POP3 protokol je:",
    "answers": [
      "stateless",
      "stateful",
      "zavisi od konfiguracije",
      "hibridni protokol"
    ],
    "correctAnswer": "stateful"
  },
  {
    "id": 11,
    "question": "IMAP protokol dozvoljava:",
    "answers": [
      "prenos fajlova",
      "kreiranje direktorijuma na serveru",
      "slanje email-a",
      "automatsko dodeljivanje IP adresa"
    ],
    "correctAnswer": "kreiranje direktorijuma na serveru"
  },
  {
    "id": 12,
    "question": "Koliko se bajtova prenese preko TCP konekcije kod HTTP-a sa nepostojanom konekcijom ako imamo HTML fajl i 10 referenci?",
    "answers": [
      "22",
      "11",
      "33",
      "44"
    ],
    "correctAnswer": "22"
  },
  {
    "id": 13,
    "question": "DNS koristi klijent server arhitekturu?",
    "answers": [
      "da",
      "ne",
      "samo za root servere",
      "samo za lokalne upite"
    ],
    "correctAnswer": "da"
  },
  {
    "id": 14,
    "question": "Root DNS server u slučaju da ne može da reši upit, šalje:",
    "answers": [
      "grešku",
      "adresu TLD servera",
      "adresu autoritativnog servera",
      "adresu lokalnog DNS-a"
    ],
    "correctAnswer": "adresu TLD servera"
  },
  {
    "id": 15,
    "question": "Local DNS server u slučaju da ne može da reši upit, šalje upit:",
    "answers": [
      "TLD serveru",
      "Root serveru",
      "autoritativnom serveru",
      "klijentu"
    ],
    "correctAnswer": "Root serveru"
  },
  {
    "id": 16,
    "question": "U kakvoj su vezi root DNS server i lokalni DNS server u slučaju rekurzivnog upita?",
    "answers": [
      "Iterativnoj",
      "Rekurzivnoj",
      "Hibridnoj",
      "Direktnoj"
    ],
    "correctAnswer": "Iterativnoj"
  },
  {
    "id": 17,
    "question": "DNS resource record Type A obezbeduje:",
    "answers": [
      "mapiranje imena u IP adresu",
      "mapiranje IP adrese u ime",
      "mapiranje aliasa servera u kanonsko ime",
      "mapiranje aliasa mail servera u kanonsko ime"
    ],
    "correctAnswer": "mapiranje imena u IP adresu"
  },
  {
    "id": 18,
    "question": "DNS resource record Type MX obezbeduje:",
    "answers": [
      "mapiranje imena u IP adresu",
      "mapiranje IP adrese u ime",
      "mapiranje aliasa servera u kanonsko ime",
      "mapiranje aliasa mail servera u kanonsko ime"
    ],
    "correctAnswer": "mapiranje aliasa mail servera u kanonsko ime"
  },
  {
    "id": 19,
    "question": "Kada se između web čitača i servera uspostavi nepostojana konekcija, u kom slučaju je moguće poslati više od jednog objekta u jednom odgovoru?",
    "answers": [
      "da",
      "ne"
    ],
    "correctAnswer": "ne"
  },
  {
    "id": 20,
    "question": "Ukoliko proširimo prethodni primer (pitanje 19) i uzmemo da se veb stranica sastoji od HTML fajla i 10 JPEG slika, koliko RTT-a nam je potrebno da preuzmemo stranicu sa njenim objektima?",
    "answers": [
      "11",
      "22",
      "33",
      "44"
    ],
    "correctAnswer": "22"
  },
  {
    "id": 21,
    "question": "Koliko bi nam Round Trip Time-ova bilo potrebno da preuzmemo stranicu sa objektima u slučaju trajne nepostojanosti sa pipeliniranjem?",
    "answers": [
      "1",
      "2",
      "3",
      "11"
    ],
    "correctAnswer": "3"
  },
  {
    "id": 22,
    "question": "Koliko bi nam RTT-ova bilo potrebno da preuzmemo stranicu sa objektima u slučaju trajne nepostojanosti bez pipeliniranja?",
    "answers": [
      "11",
      "12",
      "22",
      "3"
    ],
    "correctAnswer": "12"
  },
  {
    "id": 23,
    "question": "Šta je sadržano u DNS odgovoru?",
    "answers": [
      "name, value, type, ttl",
      "name, value, type",
      "samo IP adresa",
      "samo ime domena"
    ],
    "correctAnswer": "name, value, type, ttl"
  },
  {
    "id": 24,
    "question": "DNS keširanje se vrši na:",
    "answers": [
      "root serveru",
      "TLD serveru",
      "lokalnom DNS serveru",
      "autoritativnom serveru"
    ],
    "correctAnswer": "lokalnom DNS serveru"
  },
  {
    "id": 25,
    "question": "Da li je root DNS server deo autoritativnog DNS servera?",
    "answers": [
      "da",
      "ne"
    ],
    "correctAnswer": "ne"
  },
  {
    "id": 26,
    "question": "Veb keš se obično instalira kod:",
    "answers": [
      "korisnika",
      "Internet provajdera",
      "veb servera",
      "root DNS servera"
    ],
    "correctAnswer": "Internet provajdera"
  },
  {
    "id": 27,
    "question": "Veb keš je i server i klijent?",
    "answers": [
      "da",
      "ne",
      "samo server",
      "samo klijent"
    ],
    "correctAnswer": "da"
  },
  {
    "id": 28,
    "question": "U kom slučaju veb keš vraća originalni zahtev klijenta serveru?",
    "answers": [
      "Ako je objekat u kešu svež",
      "Ako objekt uopšte nije u kešu",
      "Ako objekat nije u kešu ili je stariji",
      "Uvek"
    ],
    "correctAnswer": "Ako objekt nije u kešu ili je stariji"
  },
  {
    "id": 29,
    "question": "Servisi koje obezbeđuje UDP su:",
    "answers": [
      "pouzdan prenos podataka i kontrola toka",
      "multipleksiranje, demultipleksiranje i provera grešaka",
      "kontrola zagušenja i uspostavljanje veze",
      "svi navedeni"
    ],
    "correctAnswer": "multipleksiranje, demultipleksiranje i provera grešaka"
  },
  {
    "id": 30,
    "question": "Koji je glavni razlog za uvođenje TCP protokola?",
    "answers": [
      "Smanjenje kompleksnosti",
      "Povećanje brzine",
      "Obezbeđenje pouzdanog prenosa",
      "Smanjenje zaglavlja"
    ],
    "correctAnswer": "Obezbeđenje pouzdanog prenosa"
  },
  {
    "id": 31,
    "question": "Da li UDP koristi handshaking?",
    "answers": [
      "da",
      "ne"
    ],
    "correctAnswer": "ne"
  },
  {
    "id": 32,
    "question": "UDP protokol koristi aplikativni sloj za:",
    "answers": [
      "proveru grešaka",
      "kontrolu toka",
      "obezbeđenje pouzdanosti",
      "multipleksiranje"
    ],
    "correctAnswer": "obezbeđenje pouzdanosti"
  },
  {
    "id": 33,
    "question": "Koji protokol koristi DNS?",
    "answers": [
      "TCP",
      "UDP",
      "ICMP",
      "HTTP"
    ],
    "correctAnswer": "UDP"
  },
  {
    "id": 34,
    "question": "Koji protokol koristi SNMP?",
    "answers": [
      "TCP",
      "UDP",
      "ICMP",
      "FTP"
    ],
    "correctAnswer": "UDP"
  },
  {
    "id": 35,
    "question": "Pretpostavite da se veb stranica sastoji od 10 objekata, a HTML dokument je osnova. Svi objekti su na istom serveru. RoundTripTime vreme je RTT. HTTP odgovor poruke mogu biti prihvaćene 100ms nakon slanja HTTP odgovora. Da li će veb stranica biti dostupna posle 2.1*RTT-a koristeći trajnu, odnosno nepostojannu konekciju?",
    "answers": [
      "tačno",
      "netačno"
    ],
    "correctAnswer": "netačno"
  },
  {
    "id": 36,
    "question": "Ukoliko proširimo prethodni primer da li će veb stranica biti dostupna posle 12*RTT-a koristeći trajnu, odnosno nepostojannu konekciju?",
    "answers": [
      "tačno",
      "netačno"
    ],
    "correctAnswer": "netačno"
  },
  {
    "id": 37,
    "question": "Da li FTP koristi out of band kontrolu?",
    "answers": [
      "da",
      "ne"
    ],
    "correctAnswer": "da"
  },
  {
    "id": 38,
    "question": "FTP zadržava stanje?",
    "answers": [
      "da",
      "ne"
    ],
    "correctAnswer": "da"
  },
  {
    "id": 39,
    "question": "SMTP koristi trajnu konekciju?",
    "answers": [
      "da",
      "ne"
    ],
    "correctAnswer": "da"
  },
  {
    "id": 40,
    "question": "SMTP zahteva da se poruka (header i body) enkodira u:",
    "answers": [
      "UTF-8",
      "7-bit ASCII",
      "Unicode",
      "Binary"
    ],
    "correctAnswer": "7-bit ASCII"
  },
  {
    "id": 41,
    "question": "Komanda CRLF.CRLF označava:",
    "answers": [
      "početak poruke",
      "kraj poruke",
      "grešku",
      "novi red"
    ],
    "correctAnswer": "kraj poruke"
  },
  {
    "id": 42,
    "question": "U slučaju slanja sa više primaoca, server identifikuje primaoce komandom:",
    "answers": [
      "MAIL FROM",
      "RCPT TO",
      "DATA",
      "HELO"
    ],
    "correctAnswer": "RCPT TO"
  },
  {
    "id": 43,
    "question": "POP3 autorizaciona faza obuhvata komande:",
    "answers": [
      "user i pass",
      "list, retr, dele",
      "quit",
      "stat"
    ],
    "correctAnswer": "user i pass"
  },
  {
    "id": 44,
    "question": "DNS resource record Type NS (name server) omogućava:",
    "answers": [
      "mapiranje domena u IP adresu autoritativnog servera",
      "mapiranje imena u IP adresu",
      "mapiranje aliasa u kanonsko ime",
      "mapiranje mail servera"
    ],
    "correctAnswer": "mapiranje domena u IP adresu autoritativnog servera"
  },
  {
    "id": 45,
    "question": "RR tip CNAME omogućava:",
    "answers": [
      "mapiranje imena u IP adresu",
      "mapiranje aliasa servera u kanonsko ime",
      "mapiranje mail servera",
      "mapiranje domena u NS"
    ],
    "correctAnswer": "mapiranje aliasa servera u kanonsko ime"
  },
  {
    "id": 46,
    "question": "Koje sve TLD postoje?",
    "answers": [
      "com",
      "org",
      "edu",
      "sve navedeno"
    ],
    "correctAnswer": "sve navedeno"
  },
  {
    "id": 47,
    "question": "Da li je DNS distribuiran?",
    "answers": [
      "da",
      "ne"
    ],
    "correctAnswer": "da"
  },
  {
    "id": 48,
    "question": "Client Server arhitektura ima:",
    "answers": [
      "server koji je uvek uključen",
      "klijent koji je uvek uključen",
      "oba su uvek uključena",
      "nijedan nije uvek uključen"
    ],
    "correctAnswer": "server koji je uvek uključen"
  },
  {
    "id": 49,
    "question": "P2P arhitektura je:",
    "answers": [
      "centralizovana",
      "decentralizovana",
      "hibridna",
      "distribuirana"
    ],
    "correctAnswer": "decentralizovana"
  },
  {
    "id": 50,
    "question": "Multipleksiranje se odnosi na:",
    "answers": [
      "slanje podataka sa više soketa preko jedne konekcije",
      "primanje podataka na više soketa sa jedne konekcije",
      "uspostavljanje više konekcija",
      "zatvaranje konekcija"
    ],
    "correctAnswer": "slanje podataka sa više soketa preko jedne konekcije"
  },
  {
    "id": 51,
    "question": "Demultipleksiranje se odnosi na:",
    "answers": [
      "slanje podataka sa više soketa",
      "primanje podataka na više soketa sa jedne konekcije",
      "zatvaranje soketa",
      "otvaranje soketa"
    ],
    "correctAnswer": "primanje podataka na više soketa sa jedne konekcije"
  },
  {
    "id": 52,
    "question": "UDP provera integritetnih grešaka se vrši pomoću:",
    "answers": [
      "CRC",
      "kontrolne sume (checksum)",
      "pariteta",
      "Hash funkcije"
    ],
    "correctAnswer": "kontrolne sume (checksum)"
  },
  {
    "id": 53,
    "question": "Kontrolna suma se računa:",
    "answers": [
      "samo nad podacima",
      "nad podacima i zaglavljem",
      "samo nad zaglavljem",
      "nad MAC adresom"
    ],
    "correctAnswer": "nad podacima i zaglavljem"
  },
  {
    "id": 54,
    "question": "Da li UDP otkriva greške?",
    "answers": [
      "da",
      "ne"
    ],
    "correctAnswer": "da"
  },
  {
    "id": 55,
    "question": "Da li UDP ispravlja greške?",
    "answers": [
      "da",
      "ne"
    ],
    "correctAnswer": "ne"
  },
  {
    "id": 56,
    "question": "Princip pouzdanog prenosa podataka obuhvata:",
    "answers": [
      "detekciju grešaka",
      "potvrde prijema",
      "ponovno slanje",
      "sve navedeno"
    ],
    "correctAnswer": "sve navedeno"
  },
  {
    "id": 57,
    "question": "Negativna potvrda (NAK) se šalje kada:",
    "answers": [
      "paket stigne ispravan",
      "paket stigne neispravan",
      "paket ne stigne",
      "uvek"
    ],
    "correctAnswer": "paket stigne neispravan"
  },
  {
    "id": 58,
    "question": "Stop and wait protokol šalje:",
    "answers": [
      "više paketa odjednom",
      "jedan paket pa čeka potvrdu",
      "pakete bez potvrde",
      "samo kontrolne pakete"
    ],
    "correctAnswer": "jedan paket pa čeka potvrdu"
  },
  {
    "id": 59,
    "question": "Go-Back-N protokol u slučaju greške:",
    "answers": [
      "šalje samo paket sa greškom",
      "šalje sve pakete od onog sa greškom",
      "ne šalje ništa",
      "šalje samo ACK"
    ],
    "correctAnswer": "šalje sve pakete od onog sa greškom"
  },
  {
    "id": 60,
    "question": "Selektivno ponavljanje (Selective Repeat) u slučaju greške:",
    "answers": [
      "šalje sve pakete",
      "šalje samo paket sa greškom",
      "ne šalje ništa",
      "čeka timeout"
    ],
    "correctAnswer": "šalje samo paket sa greškom"
  },
  {
    "id": 61,
    "question": "TCP je:",
    "answers": [
      "nepouzdan protokol",
      "pouzdan protokol",
      "hibridni protokol",
      "protokol bez konekcije"
    ],
    "correctAnswer": "pouzdan protokol"
  },
  {
    "id": 62,
    "question": "TCP segment sadrži:",
    "answers": [
      "source port, dest port, sequence number, ack number",
      "samo podatke",
      "samo adrese",
      "samo kontrolne informacije"
    ],
    "correctAnswer": "source port, dest port, sequence number, ack number"
  },
  {
    "id": 63,
    "question": "Redni broj (sequence number) u TCP-u predstavlja:",
    "answers": [
      "broj segmenta",
      "broj prvog bajta u segmentu",
      "broj paketa",
      "broj potvrde"
    ],
    "correctAnswer": "broj prvog bajta u segmentu"
  },
  {
    "id": 64,
    "question": "ACK broj u TCP-u predstavlja:",
    "answers": [
      "broj primljenog bajta",
      "broj sledećeg očekivanog bajta",
      "broj poslatog bajta",
      "broj segmenta"
    ],
    "correctAnswer": "broj sledećeg očekivanog bajta"
  },
  {
    "id": 65,
    "question": "TCP trostruko rukovanje (3-way handshake) obuhvata:",
    "answers": [
      "SYN, SYN-ACK, ACK",
      "SYN, ACK, FIN",
      "SYN, SYN, ACK",
      "ACK, ACK, ACK"
    ],
    "correctAnswer": "SYN, SYN-ACK, ACK"
  },
  {
    "id": 66,
    "question": "TCP zatvaranje konekcije se vrši sa:",
    "answers": [
      "SYN flagom",
      "FIN flagom",
      "RST flagom",
      "ACK flagom"
    ],
    "correctAnswer": "FIN flagom"
  },
  {
    "id": 67,
    "question": "Timeout interval u TCP-u se izračunava na osnovu:",
    "answers": [
      "RTT",
      "brzine linka",
      "veličine prozora",
      "broja hop-ova"
    ],
    "correctAnswer": "RTT"
  },
  {
    "id": 68,
    "question": "Brzo ponovno slanje (fast retransmit) se aktivira posle:",
    "answers": [
      "1 duplikat ACK",
      "2 duplikat ACK",
      "3 duplikat ACK",
      "4 duplikat ACK"
    ],
    "correctAnswer": "3 duplikat ACK"
  },
  {
    "id": 69,
    "question": "Kontrola toka u TCP-u se vrši pomoću:",
    "answers": [
      "receive window (rwnd)",
      "congestion window (cwnd)",
      "timeout-a",
      "checksuma"
    ],
    "correctAnswer": "receive window (rwnd)"
  },
  {
    "id": 70,
    "question": "Kontrola zagušenja u TCP-u koristi:",
    "answers": [
      "receive window",
      "congestion window (cwnd)",
      "timeout",
      "checksum"
    ],
    "correctAnswer": "congestion window (cwnd)"
  },
  {
    "id": 71,
    "question": "Slow start faza TCP-a:",
    "answers": [
      "linearno povećava cwnd",
      "eksponencijalno povećava cwnd",
      "smanjuje cwnd",
      "ne menja cwnd"
    ],
    "correctAnswer": "eksponencijalno povećava cwnd"
  },
  {
    "id": 72,
    "question": "Congestion avoidance faza TCP-a:",
    "answers": [
      "eksponencijalno povećava cwnd",
      "linearno povećava cwnd",
      "smanjuje cwnd",
      "ne menja cwnd"
    ],
    "correctAnswer": "linearno povećava cwnd"
  },
  {
    "id": 73,
    "question": "U slučaju timeout-a, TCP:",
    "answers": [
      "nastavlja normalno",
      "resetuje cwnd na 1 MSS",
      "udvostručava cwnd",
      "zatvara konekciju"
    ],
    "correctAnswer": "resetuje cwnd na 1 MSS"
  },
  {
    "id": 74,
    "question": "U slučaju 3 duplikat ACK, TCP:",
    "answers": [
      "resetuje cwnd na 1",
      "prepolovi cwnd",
      "ne menja cwnd",
      "zatvara konekciju"
    ],
    "correctAnswer": "prepolovi cwnd"
  },
  {
    "id": 75,
    "question": "TCP Reno razlikuje se od TCP Tahoe po:",
    "answers": [
      "ne razlikuje se",
      "načinu reagovanja na 3 duplikat ACK",
      "načinu rukovanja",
      "veličini prozora"
    ],
    "correctAnswer": "načinu reagovanja na 3 duplikat ACK"
  },
  {
    "id": 76,
    "question": "Fairness u TCP-u znači:",
    "answers": [
      "sve konekcije dobijaju istu propusnost",
      "server ima prioritet",
      "klijent ima prioritet",
      "nasumična raspodela"
    ],
    "correctAnswer": "sve konekcije dobijaju istu propusnost"
  },
  {
    "id": 77,
    "question": "Da li UDP obezbeđuje fairness?",
    "answers": [
      "da",
      "ne"
    ],
    "correctAnswer": "ne"
  },
  {
    "id": 78,
    "question": "Maximum Segment Size (MSS) se određuje na osnovu:",
    "answers": [
      "MTU",
      "RTT",
      "propusnosti",
      "broja hop-ova"
    ],
    "correctAnswer": "MTU"
  },
  {
    "id": 79,
    "question": "Tipična MSS vrednost je:",
    "answers": [
      "536 bajtova",
      "1460 bajtova",
      "1500 bajtova",
      "64 KB"
    ],
    "correctAnswer": "1460 bajtova"
  },
  {
    "id": 80,
    "question": "TCP kumulativne potvrde znače:",
    "answers": [
      "potvrđuje svaki paket pojedinačno",
      "potvrđuje sve do određenog broja",
      "ne potvrđuje pakete",
      "potvrđuje samo greške"
    ],
    "correctAnswer": "potvrđuje sve do određenog broja"
  },
  {
    "id": 81,
    "question": "Silly window syndrome se rešava pomoću:",
    "answers": [
      "Nagle algoritma",
      "Slow start",
      "Fast retransmit",
      "Congestion avoidance"
    ],
    "correctAnswer": "Nagle algoritma"
  },
  {
    "id": 82,
    "question": "Piggybacking u TCP-u znači:",
    "answers": [
      "slanje podataka bez potvrde",
      "kombinovanje ACK sa podacima",
      "slanje samo ACK",
      "duplikovanje paketa"
    ],
    "correctAnswer": "kombinovanje ACK sa podacima"
  },
  {
    "id": 83,
    "question": "Delayed ACK u TCP-u:",
    "answers": [
      "šalje ACK odmah",
      "čeka do 500ms pre slanja ACK",
      "ne šalje ACK",
      "šalje ACK nakon svakog paketa"
    ],
    "correctAnswer": "čeka do 500ms pre slanja ACK"
  },
  {
    "id": 84,
    "question": "Koliko bitova ima TCP header bez opcija?",
    "answers": [
      "160 bitova (20 bajtova)",
      "128 bitova",
      "256 bitova",
      "64 bitova"
    ],
    "correctAnswer": "160 bitova (20 bajtova)"
  },
  {
    "id": 85,
    "question": "Koliko bitova ima UDP header?",
    "answers": [
      "32 bita",
      "64 bita (8 bajtova)",
      "128 bitova",
      "160 bitova"
    ],
    "correctAnswer": "64 bita (8 bajtova)"
  },
  {
    "id": 86,
    "question": "TCP je full-duplex?",
    "answers": [
      "da",
      "ne"
    ],
    "correctAnswer": "da"
  },
  {
    "id": 87,
    "question": "TCP garantuje redosled isporuke paketa?",
    "answers": [
      "da",
      "ne"
    ],
    "correctAnswer": "da"
  },
  {
    "id": 88,
    "question": "UDP garantuje redosled isporuke paketa?",
    "answers": [
      "da",
      "ne"
    ],
    "correctAnswer": "ne"
  },
  {
    "id": 89,
    "question": "Koji protokol koristi streaming video?",
    "answers": [
      "TCP",
      "UDP",
      "oba",
      "nijedan"
    ],
    "correctAnswer": "UDP"
  },
  {
    "id": 90,
    "question": "Koji protokol koristi HTTP?",
    "answers": [
      "UDP",
      "TCP",
      "ICMP",
      "oba TCP i UDP"
    ],
    "correctAnswer": "TCP"
  },
  {
    "id": 91,
    "question": "Koliko wynda ima TCP?",
    "answers": [
      "1 - receive window",
      "2 - receive i congestion window",
      "3",
      "4"
    ],
    "correctAnswer": "2 - receive i congestion window"
  },
  {
    "id": 92,
    "question": "Efektivni window u TCP-u je:",
    "answers": [
      "rwnd",
      "cwnd",
      "min(rwnd, cwnd)",
      "max(rwnd, cwnd)"
    ],
    "correctAnswer": "min(rwnd, cwnd)"
  },
  {
    "id": 93,
    "question": "Multiplicative decrease u TCP-u znači:",
    "answers": [
      "linearno smanjenje cwnd",
      "prepolovljavanje cwnd",
      "resetovanje cwnd na 1",
      "udvostručavanje cwnd"
    ],
    "correctAnswer": "prepolovljavanje cwnd"
  },
  {
    "id": 94,
    "question": "Additive increase u TCP-u znači:",
    "answers": [
      "eksponencijalno povećanje",
      "linearno povećanje za 1 MSS po RTT",
      "prepolovljavanje",
      "ne menja se"
    ],
    "correctAnswer": "linearno povećanje za 1 MSS po RTT"
  },
  {
    "id": 95,
    "question": "AIMD (Additive Increase Multiplicative Decrease) se koristi u:",
    "answers": [
      "UDP",
      "TCP congestion avoidance fazi",
      "DNS",
      "HTTP"
    ],
    "correctAnswer": "TCP congestion avoidance fazi"
  },
  {
    "id": 96,
    "question": "Threshold (ssthresh) u TCP-u određuje:",
    "answers": [
      "maksimalni cwnd",
      "prelaz sa slow start na congestion avoidance",
      "minimalni cwnd",
      "MSS vrednost"
    ],
    "correctAnswer": "prelaz sa slow start na congestion avoidance"
  },
  {
    "id": 97,
    "question": "Nakon timeout-a, ssthresh se postavlja na:",
    "answers": [
      "1 MSS",
      "polovina cwnd pre timeout-a",
      "2 MSS",
      "maksimalna vrednost"
    ],
    "correctAnswer": "polovina cwnd pre timeout-a"
  },
  {
    "id": 98,
    "question": "Prednosti DNS keširanja su:",
    "answers": [
      "Povećava ažurnost podataka",
      "Smanjuje broj DNS poruka koje se kreću Internetom",
      "Povećava efikasnost DNS usluge",
      "Pojednostavljuje održavanje DNS baze"
    ],
    "correctAnswer": ["Smanjuje broj DNS poruka koje se kreću Internetom", "Povećava efikasnost DNS usluge"]
  },
  {
    "id": 99,
    "question": "Well-known portovi su u opsegu:",
    "answers": [
      "0-1023",
      "1024-49151",
      "49152-65535",
      "0-65535"
    ],
    "correctAnswer": "0-1023"
  },
  {
    "id": 100,
    "question": "Registered portovi su u opsegu:",
    "answers": [
      "0-1023",
      "1024-49151",
      "49152-65535",
      "0-255"
    ],
    "correctAnswer": "1024-49151"
  },
  {
    "id": 101,
    "question": "Dynamic/Private portovi su u opsegu:",
    "answers": [
      "0-1023",
      "1024-49151",
      "49152-65535",
      "0-65535"
    ],
    "correctAnswer": "49152-65535"
  },
  {
    "id": 102,
    "question": "HTTP koristi port:",
    "answers": [
      "20",
      "21",
      "80",
      "443"
    ],
    "correctAnswer": "80"
  },
  {
    "id": 103,
    "question": "HTTPS koristi port:",
    "answers": [
      "80",
      "443",
      "8080",
      "22"
    ],
    "correctAnswer": "443"
  },
  {
    "id": 104,
    "question": "FTP kontrolna konekcija koristi port:",
    "answers": [
      "20",
      "21",
      "22",
      "23"
    ],
    "correctAnswer": "21"
  },
  {
    "id": 105,
    "question": "FTP data konekcija koristi port:",
    "answers": [
      "20",
      "21",
      "22",
      "23"
    ],
    "correctAnswer": "20"
  },
  {
    "id": 106,
    "question": "SSH koristi port:",
    "answers": [
      "21",
      "22",
      "23",
      "25"
    ],
    "correctAnswer": "22"
  },
  {
    "id": 107,
    "question": "Telnet koristi port:",
    "answers": [
      "21",
      "22",
      "23",
      "25"
    ],
    "correctAnswer": "23"
  },
  {
    "id": 108,
    "question": "SMTP koristi port:",
    "answers": [
      "22",
      "23",
      "25",
      "53"
    ],
    "correctAnswer": "25"
  },
  {
    "id": 109,
    "question": "DNS koristi port:",
    "answers": [
      "25",
      "53",
      "80",
      "110"
    ],
    "correctAnswer": "53"
  },
  {
    "id": 110,
    "question": "POP3 koristi port:",
    "answers": [
      "80",
      "110",
      "143",
      "443"
    ],
    "correctAnswer": "110"
  },
  {
    "id": 111,
    "question": "IMAP koristi port:",
    "answers": [
      "110",
      "143",
      "443",
      "993"
    ],
    "correctAnswer": "143"
  },
  {
    "id": 112,
    "question": "DHCP server koristi port:",
    "answers": [
      "67",
      "68",
      "53",
      "80"
    ],
    "correctAnswer": "67"
  },
  {
    "id": 113,
    "question": "DHCP klijent koristi port:",
    "answers": [
      "67",
      "68",
      "69",
      "70"
    ],
    "correctAnswer": "68"
  },
  {
    "id": 114,
    "question": "TFTP koristi port:",
    "answers": [
      "68",
      "69",
      "70",
      "80"
    ],
    "correctAnswer": "69"
  },
  {
    "id": 115,
    "question": "HTTP status kod 200 znači:",
    "answers": [
      "OK - uspešan zahtev",
      "Not Found",
      "Internal Server Error",
      "Moved Permanently"
    ],
    "correctAnswer": "OK - uspešan zahtev"
  },
  {
    "id": 116,
    "question": "HTTP status kod 404 znači:",
    "answers": [
      "OK",
      "Not Found - traženi resurs ne postoji",
      "Internal Server Error",
      "Bad Request"
    ],
    "correctAnswer": "Not Found - traženi resurs ne postoji"
  },
  {
    "id": 117,
    "question": "HTTP metode su:",
    "answers": [
      "GET",
      "POST",
      "PUT",
      "DELETE",
      "HEAD"
    ],
    "correctAnswer": ["GET", "POST", "PUT"]
  }
]
